riscarchi.srcs/sources_1/new/dmem.v
module dmem(
input wire clk,
input wire we, // store when 1
input wire [31:0] addr, // byte address
input wire [31:0] wdata,
output reg [31:0] rdata
);
parameter SIZE = 256;
reg [31:0] mem [0:SIZE-1];
wire [31:0] idx = addr >> 2;


// synchronous write
always @(posedge clk) begin
if (we) begin
mem[idx] <= wdata;
// optional debug
// $display("DMEM: write addr=%0d data=%0h", idx, wdata);
end
end


// asynchronous read (simple)
always @(*) begin
rdata = mem[idx];
end
endmodule

riscarchi.srcs/sources_1/new/alu.v
module alu(
input wire [31:0] a,
input wire [31:0] b,
input wire [3:0] ctrl, // 4-bit alu control
output reg [31:0] y,
output wire zero
);
always @(*) begin
case (ctrl)
4'b0000: y = a + b; // add
4'b0001: y = a - b; // sub
4'b0010: y = a & b; // and
4'b0011: y = a | b; // or
4'b0100: y = (a < b) ? 32'd1 : 32'd0; // slt (unsigned not implemented)
default: y = 32'd0;
endcase
end


assign zero = (y == 32'd0);
endmodule

riscarchi.srcs/sources_1/new/control.v
module control(
input wire [6:0] opcode,
input wire [2:0] funct3,
input wire [6:0] funct7,
output reg alu_src,
output reg mem_to_reg,
output reg reg_write,
output reg mem_read,
output reg mem_write,
output reg branch,
output reg jal,
output reg [3:0] alu_ctrl);

always @(*) begin
// defaults
alu_src = 1'b0;
mem_to_reg = 1'b0;
reg_write = 1'b0;
mem_read = 1'b0;
mem_write = 1'b0;
branch = 1'b0;
jal = 1'b0;
alu_ctrl = 4'b0000;


case (opcode)
7'b0110011: begin // R-type (add, sub, and, or)
alu_src = 1'b0;
mem_to_reg = 1'b0;
reg_write = 1'b1;
mem_read = 1'b0;
mem_write = 1'b0;
branch = 1'b0;
// decode funct3/funct7
if (funct3 == 3'b000) begin
if (funct7 == 7'b0100000) alu_ctrl = 4'b0001; // sub
else alu_ctrl = 4'b0000; // add
end else if (funct3 == 3'b111) alu_ctrl = 4'b0010; // and
else if (funct3 == 3'b110) alu_ctrl = 4'b0011; // or
else alu_ctrl = 4'b0000;
end

7'b0010011: begin // I-type (addi)
alu_src = 1'b1;
mem_to_reg = 1'b1;
reg_write = 1'b1;
mem_read = 1'b1;
alu_ctrl = 4'b0000; // compute address with add
end


7'b0100011: begin // sw
alu_src = 1'b1;
mem_to_reg = 1'b0;
reg_write = 1'b0;
mem_write = 1'b1;
alu_ctrl = 4'b0000; // compute address with add
end


7'b1100011: begin // beq
alu_src = 1'b0;
mem_to_reg = 1'b0;
reg_write = 1'b0;
branch = 1'b1;
alu_ctrl = 4'b0001; // sub to compare
end


7'b1101111: begin // jal
alu_src = 1'b0;
mem_to_reg = 1'b0;
reg_write = 1'b1; // write PC+4 to rd
jal = 1'b1;
end


7'b1100111: begin // jalr
alu_src = 1'b1; // compute target rs1+imm
mem_to_reg = 1'b0;
reg_write = 1'b1;
jal = 1'b1; // treat as jump
alu_ctrl = 4'b0000;
end


default: begin
// nop / unsupported
end
endcase
end
endmodule

riscarchi.srcs/sources_1/new/regfile.v
module regfile(
input wire clk,
input wire we, // write enable
input wire [4:0] rs1,
input wire [4:0] rs2,
input wire [4:0] rd,
input wire [31:0] wd,
output wire [31:0] rd1,
output wire [31:0] rd2
);
reg [31:0] regs [0:31];
integer i;
initial begin
for (i=0;i<32;i=i+1) regs[i] = 32'b0;
end


// reads are asynchronous (combinational)
assign rd1 = (rs1 == 0) ? 32'b0 : regs[rs1];
assign rd2 = (rs2 == 0) ? 32'b0 : regs[rs2];


// write on rising edge
always @(posedge clk) begin
if (we && rd != 5'd0) begin
regs[rd] <= wd;
// optional debug
// $display("RF: write x%0d = %0d (0x%h)", rd, regs[rd], regs[rd]);
end
end
endmodule

riscarchi.srcs/sources_1/new/imm_gen.v
module imm_gen(
input wire [31:0] instr,
output reg [31:0] imm_out
);
wire [6:0] opcode = instr[6:0];
always @(*) begin
case (opcode)
7'b0010011: begin // I-type (addi)
imm_out = {{20{instr[31]}}, instr[31:20]};
end
7'b0000011: begin // lw (I-type)
imm_out = {{20{instr[31]}}, instr[31:20]};
end
7'b1100111: begin // jalr (I-type)
imm_out = {{20{instr[31]}}, instr[31:20]};
end
7'b0100011: begin // S-type (sw)
imm_out = {{20{instr[31]}}, instr[31:25], instr[11:7]};
end
7'b1100011: begin // B-type (beq)
// imm = {instr[31], instr[7], instr[30:25], instr[11:8], 1'b0}
imm_out = {{19{instr[31]}}, instr[31], instr[7], instr[30:25], instr[11:8], 1'b0};
end
7'b1101111: begin // J-type (jal)
// imm = {instr[31], instr[19:12], instr[20], instr[30:21], 1'b0}
imm_out = {{11{instr[31]}}, instr[31], instr[19:12], instr[20], instr[30:21], 1'b0};
end
7'b0110111: begin // LUI (U-type)
imm_out = {instr[31:12], 12'b0};
end
7'b0010111: begin // AUIPC (U-type)
imm_out = {instr[31:12], 12'b0};
end
default: imm_out = 32'd0;
endcase
end
endmodule

riscarchi.srcs/sources_1/new/imem.v
module imem(
input wire [31:0] addr, // byte address
output wire [31:0] instr
);
parameter SIZE = 256; // number of 32-bit words
reg [31:0] mem [0:SIZE-1];
wire [31:0] idx = addr >> 2;


initial begin
// Default program file name. Create program.mem next to your sources
// Format: one 32-bit hex word per line (e.g. 00500093)
$display("IMEM: Loading program.mem (make sure the file exists in simulation directory)");
$readmemh("program.mem", mem);
end


assign instr = mem[idx];
endmodule

riscarchi.srcs/sources_1/new/riscv_core_top.v
// ---------------------------------
// File: riscv_core_top.v
// Single-cycle RISC-V (RV32I subset) CPU core
// ---------------------------------
module riscv_core_top(
    input wire clk,
    input wire rst
);
    // Program Counter
    reg [31:0] pc;
    wire [31:0] instr;

    // Instruction Memory
    imem imem_i(.addr(pc), .instr(instr));

    // Instruction fields
    wire [6:0] opcode = instr[6:0];
    wire [4:0] rd     = instr[11:7];
    wire [2:0] funct3 = instr[14:12];
    wire [4:0] rs1    = instr[19:15];
    wire [4:0] rs2    = instr[24:20];
    wire [6:0] funct7 = instr[31:25];

    // Immediate Generator
    wire [31:0] imm;
    imm_gen immgen(.instr(instr), .imm_out(imm));

    // Register File
    wire [31:0] reg_r1, reg_r2;
    reg reg_we;
    reg [4:0] reg_rd;
    reg [31:0] reg_wd;
    regfile regs(
        .clk(clk),
        .we(reg_we),
        .rs1(rs1),
        .rs2(rs2),
        .rd(reg_rd),
        .wd(reg_wd),
        .rd1(reg_r1),
        .rd2(reg_r2)
    );

    // Control Unit
    wire alu_src, mem_to_reg, reg_write, mem_read, mem_write, branch, jal;
    wire [3:0] alu_ctrl;
    control ctrl(
        .opcode(opcode), .funct3(funct3), .funct7(funct7),
        .alu_src(alu_src), .mem_to_reg(mem_to_reg), .reg_write(reg_write),
        .mem_read(mem_read), .mem_write(mem_write),
        .branch(branch), .jal(jal), .alu_ctrl(alu_ctrl)
    );

    // ALU
    reg [31:0] alu_b;
    wire [31:0] alu_result;
    wire alu_zero;
    alu alu_i(.a(reg_r1), .b(alu_b), .ctrl(alu_ctrl), .y(alu_result), .zero(alu_zero));

    // Data Memory
    wire [31:0] dmem_rdata;
    dmem dmem_i(.clk(clk), .we(mem_write), .addr(alu_result), .wdata(reg_r2), .rdata(dmem_rdata));

    // Next PC
    reg [31:0] pc_next;

    // Main control and writeback
    always @(*) begin
        // Defaults
        alu_b   = reg_r2;
        reg_we  = 1'b0;
        reg_rd  = rd;
        reg_wd  = 32'd0;
        pc_next = pc + 4;

        // ALU operand select
        if (alu_src) alu_b = imm;

        // Branch target
        if (branch && alu_zero) begin
            pc_next = pc + imm;
        end

        // Jump target
        if (jal) begin
            pc_next = pc + imm;
        end

        // Write-back data
        if (mem_to_reg) begin
            reg_wd = dmem_rdata;
        end else begin
            if (jal) reg_wd = pc + 4;  // for JAL, write return address
            else reg_wd = alu_result;
        end

        // Register write enable
        if (reg_write) reg_we = 1'b1;
    end

    // PC update
    always @(posedge clk or posedge rst) begin
        if (rst) pc <= 32'd0;
        else pc <= pc_next;
    end

endmodule

riscarchi.srcs/sim_1/new/testbench.v
module tb_riscv;
reg clk;
reg rst;


riscv_core_top dut(.clk(clk), .rst(rst));


initial begin
//$dumpfile("wave.vcd");
//$dumpvars(0, tb_riscv);


clk = 0;
rst = 1;
#20;
rst = 0;


// run for a while
#1000;
$display("Simulation finished");
$finish;
end


always #5 clk = ~clk; // 100MHz-ish clock in simulation time units
endmodule

riscarchi.sim/sim_1/behav/xsim/wave.vcd
$date
   Sun Sep 14 18:05:59 2025
$end
$version
  2020.2
$end
$timescale
  1ps
$end
$scope module tb_riscv $end
$var reg 1 ! clk $end
$var reg 1 " rst $end
$scope module dut $end
$var wire 1 # clk $end
$var wire 1 $ rst $end
$var reg 32 % pc [31:0] $end
$var wire 32 & instr [31:0] $end
$var wire 7 ' opcode [6:0] $end
$var wire 5 ( rd [4:0] $end
$var wire 3 ) funct3 [2:0] $end
$var wire 5 * rs1 [4:0] $end
$var wire 5 + rs2 [4:0] $end
$var wire 7 , funct7 [6:0] $end
$var wire 32 - imm [31:0] $end
$var wire 32 . reg_r1 [31:0] $end
$var wire 32 / reg_r2 [31:0] $end
$var reg 1 0 reg_we $end
$var reg 5 1 reg_rd [4:0] $end
$var reg 32 2 reg_wd [31:0] $end
$var wire 1 3 alu_src $end
$var wire 1 4 mem_to_reg $end
$var wire 1 5 reg_write $end
$var wire 1 6 mem_read $end
$var wire 1 7 mem_write $end
$var wire 1 8 branch $end
$var wire 1 9 jal $end
$var wire 4 : alu_ctrl [3:0] $end
$var reg 32 ; alu_b [31:0] $end
$var wire 32 < alu_result [31:0] $end
$var wire 1 = alu_zero $end
$var wire 32 > dmem_rdata [31:0] $end
$var reg 32 ? pc_next [31:0] $end
$scope module imem_i $end
$var wire 32 @ addr [31:0] $end
$var wire 32 & instr [31:0] $end
$var wire 32 A idx [31:0] $end
$var parameter 32 B SIZE [31:0] $end
$upscope $end
$scope module immgen $end
$var wire 32 & instr [31:0] $end
$var reg 32 C imm_out [31:0] $end
$var wire 7 D opcode [6:0] $end
$upscope $end
$scope module regs $end
$var wire 1 # clk $end
$var wire 1 E we $end
$var wire 5 * rs1 [4:0] $end
$var wire 5 + rs2 [4:0] $end
$var wire 5 F rd [4:0] $end
$var wire 32 G wd [31:0] $end
$var wire 32 . rd1 [31:0] $end
$var wire 32 / rd2 [31:0] $end
$var integer 32 H i $end
$upscope $end
$scope module ctrl $end
$var wire 7 ' opcode [6:0] $end
$var wire 3 ) funct3 [2:0] $end
$var wire 7 , funct7 [6:0] $end
$var reg 1 I alu_src $end
$var reg 1 J mem_to_reg $end
$var reg 1 K reg_write $end
$var reg 1 L mem_read $end
$var reg 1 M mem_write $end
$var reg 1 N branch $end
$var reg 1 O jal $end
$var reg 4 P alu_ctrl [3:0] $end
$upscope $end
$scope module alu_i $end
$var wire 32 . a [31:0] $end
$var wire 32 Q b [31:0] $end
$var wire 4 : ctrl [3:0] $end
$var reg 32 R y [31:0] $end
$var wire 1 = zero $end
$upscope $end
$scope module dmem_i $end
$var wire 1 # clk $end
$var wire 1 7 we $end
$var wire 32 < addr [31:0] $end
$var wire 32 / wdata [31:0] $end
$var reg 32 S rdata [31:0] $end
$var wire 32 T idx [31:0] $end
$var parameter 32 U SIZE [31:0] $end
$upscope $end
$upscope $end
$upscope $end
$enddefinitions $end
#0
$dumpvars
0!
1"
0#
1$
b0 %
b10100000000000010010011 &
b10011 '
b1 (
b0 )
b0 *
b101 +
b0 ,
b101 -
b0 .
b0 /
10
b1 1
bx 2
03
14
15
16
07
08
09
b0 :
b0 ;
b0 <
1=
bx >
b100 ?
b0 @
b0 A
b100000000 B
b101 C
b10011 D
1E
b1 F
bx G
b100000 H
0I
1J
1K
1L
0M
0N
0O
b0 P
b0 Q
b0 R
bx S
b0 T
b100000000 U
$end
#5000
1!
1#
b0 .
b0 /
#10000
0!
0#
#15000
1!
1#
#20000
0!
0"
0#
0$
#25000
1!
1#
b100 %
b101000000000000100010011 &
b10 (
b1010 +
b1010 -
b0 /
10
b10 1
bx 2
b0 ;
b1000 ?
b100 @
b1 A
b1010 C
b10 F
#30000
0!
0#
#35000
1!
1#
b1000 %
b1000001000000110110011 &
b110011 '
b11 (
b1 *
b10 +
b0 -
bx .
bx /
10
b11 1
bx 2
04
15
06
bx ;
bx <
x=
b1100 ?
b1000 @
b10 A
b0 C
b110011 D
b11 F
0I
0J
1K
0L
0M
0N
0O
b0 P
bx Q
bx R
bx S
b0xxxxxxxxxxxxxxxxxxxxxxxxxxxxxx T
#40000
0!
0#
#45000
1!
1#
b1100 %
b1100000010000000100011 &
b100011 '
b0 (
b10 )
b0 *
b11 +
b0 .
bx /
00
b0 1
b0 2
13
05
17
b0 ;
b0 <
1=
b10000 ?
b1100 @
b11 A
b0 C
b100011 D
0E
b0 F
b0 G
1I
0J
0K
0L
1M
0N
0O
b0 P
b0 Q
b0 R
bx S
b0 T
#50000
0!
0#
#55000
1!
1#
b10000 %
b10001000000011 &
b11 '
b100 (
b0 +
b0 /
b100 1
b0 2
03
07
b0 ;
b10100 ?
b10000 @
b100 A
b0 C
b11 D
b100 F
0I
0J
0K
0L
0M
0N
0O
b0 P
b0 Q
#60000
0!
0#
#65000
1!
1#
b10100 %
b100100000001010010011 &
b10011 '
b101 (
b0 )
b100 *
b1 +
b1 -
b0 .
bx /
10
b101 1
bx 2
14
15
16
bx ;
bx <
x=
b11000 ?
b10100 @
b101 A
b1 C
b10011 D
1E
b101 F
bx G
0I
1J
1K
1L
0M
0N
0O
b0 P
bx Q
bx R
bx S
b0xxxxxxxxxxxxxxxxxxxxxxxxxxxxxx T
#70000
0!
0#
#75000
1!
1#
b11000 %
b1101111 &
b1101111 '
b0 (
b0 *
b0 +
b0 -
b0 .
b0 /
10
b0 1
b11100 2
04
15
06
19
b0 ;
b0 <
1=
b11000 ?
b11000 @
b110 A
b0 C
b1101111 D
b0 F
b11100 G
0I
0J
1K
0L
0M
0N
1O
b0 P
b0 Q
b0 R
bx S
b0 T
